Metadata-Version: 1.0
Name: jojo-tmp
Version: 0.0.1
Summary: 吃枣药丸
Home-page: https://zhuanlan.zhihu.com/p/26159930
Author: Joe_yoy
Author-email: Joe_yoy@outlook.com
License: MIT
Platform: UNKNOWN
